datasette_template_request/__init__.py
datasette_template_request-0.1.dist-info/METADATA
datasette_template_request-0.1.dist-info/WHEEL
datasette_template_request-0.1.dist-info/entry_points.txt
datasette_template_request-0.1.dist-info/top_level.txt
datasette_template_request-0.1.dist-info/RECORD
