Metadata-Version: 2.1
Name: datasette-template-request
Version: 0.1
Summary: Expose the Datasette request object to custom templates
Home-page: https://github.com/simonw/datasette-template-request
Author: Simon Willison
License: Apache License, Version 2.0
Project-URL: Issues, https://github.com/simonw/datasette-template-request/issues
Project-URL: CI, https://github.com/simonw/datasette-template-request/actions
Project-URL: Changelog, https://github.com/simonw/datasette-template-request/releases
Platform: UNKNOWN
Requires-Python: >=3.6
Requires-Dist: datasette
Provides-Extra: test
Requires-Dist: pytest ; extra == 'test'
Requires-Dist: pytest-asyncio ; extra == 'test'
